README.md
setup.py
carefree_client.egg-info/PKG-INFO
carefree_client.egg-info/SOURCES.txt
carefree_client.egg-info/dependency_links.txt
carefree_client.egg-info/requires.txt
carefree_client.egg-info/top_level.txt
cfclient/__init__.py
cfclient/core.py
cfclient/utils.py
cfclient/models/__init__.py
cfclient/models/constants.py
cfclient/models/core.py
cfclient/models/demo.py