Metadata-Version: 2.1
Name: carefree-client
Version: 0.1.9
Summary: Client framework based on FastAPI
Author: carefree0910
Author-email: syameimaru.saki@gmail.com
Keywords: python carefree-learn PyTorch
